pulumi_signalfx/__init__.py
pulumi_signalfx/_inputs.py
pulumi_signalfx/_utilities.py
pulumi_signalfx/alert_muting_rule.py
pulumi_signalfx/dashboard.py
pulumi_signalfx/dashboard_group.py
pulumi_signalfx/data_link.py
pulumi_signalfx/detector.py
pulumi_signalfx/event_feed_chart.py
pulumi_signalfx/get_dimension_values.py
pulumi_signalfx/heatmap_chart.py
pulumi_signalfx/list_chart.py
pulumi_signalfx/metric_ruleset.py
pulumi_signalfx/org_token.py
pulumi_signalfx/organization_members.py
pulumi_signalfx/outputs.py
pulumi_signalfx/provider.py
pulumi_signalfx/pulumi-plugin.json
pulumi_signalfx/py.typed
pulumi_signalfx/single_value_chart.py
pulumi_signalfx/slo.py
pulumi_signalfx/slo_chart.py
pulumi_signalfx/table_chart.py
pulumi_signalfx/team.py
pulumi_signalfx/text_chart.py
pulumi_signalfx/time_chart.py
pulumi_signalfx/webhook_integration.py
pulumi_signalfx/automatedarchival/__init__.py
pulumi_signalfx/automatedarchival/_inputs.py
pulumi_signalfx/automatedarchival/exempt_metric.py
pulumi_signalfx/automatedarchival/outputs.py
pulumi_signalfx/automatedarchival/settings.py
pulumi_signalfx/aws/__init__.py
pulumi_signalfx/aws/_inputs.py
pulumi_signalfx/aws/external_integration.py
pulumi_signalfx/aws/integration.py
pulumi_signalfx/aws/outputs.py
pulumi_signalfx/aws/token_integration.py
pulumi_signalfx/azure/__init__.py
pulumi_signalfx/azure/_inputs.py
pulumi_signalfx/azure/integration.py
pulumi_signalfx/azure/outputs.py
pulumi_signalfx/config/__init__.py
pulumi_signalfx/config/__init__.pyi
pulumi_signalfx/config/vars.py
pulumi_signalfx/gcp/__init__.py
pulumi_signalfx/gcp/_inputs.py
pulumi_signalfx/gcp/integration.py
pulumi_signalfx/gcp/outputs.py
pulumi_signalfx/jira/__init__.py
pulumi_signalfx/jira/integration.py
pulumi_signalfx/log/__init__.py
pulumi_signalfx/log/_inputs.py
pulumi_signalfx/log/outputs.py
pulumi_signalfx/log/timeline.py
pulumi_signalfx/log/view.py
pulumi_signalfx/opsgenie/__init__.py
pulumi_signalfx/opsgenie/integration.py
pulumi_signalfx/pagerduty/__init__.py
pulumi_signalfx-7.21.0.dist-info/METADATA
pulumi_signalfx-7.21.0.dist-info/WHEEL
pulumi_signalfx-7.21.0.dist-info/top_level.txt
pulumi_signalfx-7.21.0.dist-info/RECORD
